StreamDeck/DeviceManager.py
StreamDeck/ProductIDs.py
StreamDeck/__init__.py
StreamDeck/Devices/LoupeDeckConstants.py
StreamDeck/Devices/Loupedeck.py
StreamDeck/Devices/LoupedeckLive.py
StreamDeck/Devices/Mirabox293S.py
StreamDeck/Devices/StreamDeck.py
StreamDeck/Devices/StreamDeckMini.py
StreamDeck/Devices/StreamDeckNeo.py
StreamDeck/Devices/StreamDeckOriginal.py
StreamDeck/Devices/StreamDeckOriginalV2.py
StreamDeck/Devices/StreamDeckPedal.py
StreamDeck/Devices/StreamDeckPlus.py
StreamDeck/Devices/StreamDeckXL.py
StreamDeck/Devices/__init__.py
StreamDeck/Devices/__pycache__/LoupeDeckConstants.cpython-313.pyc
StreamDeck/Devices/__pycache__/Loupedeck.cpython-313.pyc
StreamDeck/Devices/__pycache__/LoupedeckLive.cpython-313.pyc
StreamDeck/Devices/__pycache__/Mirabox293S.cpython-313.pyc
StreamDeck/Devices/__pycache__/StreamDeck.cpython-313.pyc
StreamDeck/Devices/__pycache__/StreamDeckMini.cpython-313.pyc
StreamDeck/Devices/__pycache__/StreamDeckNeo.cpython-313.pyc
StreamDeck/Devices/__pycache__/StreamDeckOriginal.cpython-313.pyc
StreamDeck/Devices/__pycache__/StreamDeckOriginalV2.cpython-313.pyc
StreamDeck/Devices/__pycache__/StreamDeckPedal.cpython-313.pyc
StreamDeck/Devices/__pycache__/StreamDeckPlus.cpython-313.pyc
StreamDeck/Devices/__pycache__/StreamDeckXL.cpython-313.pyc
StreamDeck/Devices/__pycache__/__init__.cpython-313.pyc
StreamDeck/ImageHelpers/PILHelper.py
StreamDeck/ImageHelpers/__init__.py
StreamDeck/ImageHelpers/__pycache__/PILHelper.cpython-313.pyc
StreamDeck/ImageHelpers/__pycache__/__init__.cpython-313.pyc
StreamDeck/Transport/Dummy.py
StreamDeck/Transport/LibUSBHIDAPI.py
StreamDeck/Transport/Transport.py
StreamDeck/Transport/__init__.py
StreamDeck/Transport/__pycache__/Dummy.cpython-313.pyc
StreamDeck/Transport/__pycache__/LibUSBHIDAPI.cpython-313.pyc
StreamDeck/Transport/__pycache__/Transport.cpython-313.pyc
StreamDeck/Transport/__pycache__/__init__.cpython-313.pyc
StreamDeck/__pycache__/DeviceManager.cpython-313.pyc
streamcontroller_streamdeck-0.1.5.dist-info/licenses/LICENSE
streamcontroller_streamdeck-0.1.5.dist-info/METADATA
streamcontroller_streamdeck-0.1.5.dist-info/WHEEL
streamcontroller_streamdeck-0.1.5.dist-info/top_level.txt
streamcontroller_streamdeck-0.1.5.dist-info/RECORD
