Metadata-Version: 2.4
Name: streamcontroller-streamdeck
Version: 0.1.5
Summary: Library to control Elgato StreamDeck devices.
Home-page: https://github.com/StreamController/sc-python-elgato-streamdeck
Author: Core447
Author-email: core447@proton.me
License: MIT
Requires-Python: >=3.8
License-File: LICENSE
Dynamic: author
Dynamic: author-email
Dynamic: description
Dynamic: description-content-type
Dynamic: home-page
Dynamic: license
Dynamic: license-file
Dynamic: requires-python
Dynamic: summary
